{
"cards":[
    {
      "scenario": "You're at home feeling thirsty. You head to the kitchen. Where do you get water from?",
      "alternatives": [
        {"choice": "Bottled Water", "co2": 20},
        {"choice": "Tap Water", "co2": 10}
      ],
      "difficulty": "Medium"
    },
    {
      "scenario": "You need a coffee before work. Which cup do you use?",
      "alternatives": [
        {"choice": "Disposable cup", "co2": 30},
        {"choice": "Thermos", "co2": 15}
      ],
      "difficulty": "Hard"
    },
    {
      "scenario": "Feeling a little hungry, you grab a snack pack. Which size do you pick?",
      "alternatives": [
        {"choice": "Small pack", "co2": 10},
        {"choice": "Family-size", "co2": 4}
      ],
      "difficulty": "Medium"
    },
    {
      "scenario": "Packing your lunch for school or work. How do you wrap your sandwich?",
      "alternatives": [
        {"choice": "Foil", "co2": 8},
        {"choice": "Beeswax", "co2": 2}
      ],
      "difficulty": "Easy"
    },
    {
      "scenario": "It's time to brush your teeth. Which toothbrush do you pick?",
      "alternatives": [
        {"choice": "Plastic", "co2": 5},
        {"choice": "Bamboo", "co2": 2}
      ],
      "difficulty": "Easy"
    },
    {
      "scenario": "You need to get to work or school. How do you make a short trip?",
      "alternatives": [
        {"choice": "Drive short trip", "co2": 25},
        {"choice": "Walk", "co2": 0}
      ],
      "difficulty": "Easy"
    },
    {
      "scenario": "Listening to music on your way. Do you stream it or play offline?",
      "alternatives": [
        {"choice": "Streaming", "co2": 6},
        {"choice": "Offline MP3", "co2": 2}
      ],
      "difficulty": "Easy"
    },
    {
      "scenario": "Studying for exams. Do you print your notes or use them digitally?",
      "alternatives": [
        {"choice": "Print", "co2": 15},
        {"choice": "Digital", "co2": 2}
      ],
      "difficulty": "Easy"
    },
    {
      "scenario": "Charging your phone. Do you leave it overnight or unplug at 100%?",
      "alternatives": [
        {"choice": "Overnight", "co2": 4},
        {"choice": "Stop at 100%", "co2": 1}
      ],
      "difficulty": "Easy"
    },
    {
      "scenario": "Packing your lunch. Which lunch box do you bring?",
      "alternatives": [
        {"choice": "Disposable", "co2": 10},
        {"choice": "Reusable", "co2": 3}
      ],
      "difficulty": "Easy"
    },
    {
      "scenario": "You're looking for a snack. Red Bull, Snickers, or tap water?",
      "alternatives": [
        {"choice": "Red Bull", "co2": 12},
        {"choice": "Snickers", "co2": 18},
        {"choice": "Tap water", "co2": 1}
      ],
      "difficulty": "Easy"
    },
    {
      "scenario": "Coffee break! Which coffee style do you choose?",
      "alternatives": [
        {"choice": "Paper cup w/ lid", "co2": 15},
        {"choice": "No lid", "co2": 10},
        {"choice": "Thermos", "co2": 2}
      ],
      "difficulty": "Easy"
    },
    {
      "scenario": "Fruits for snacks! Do you pick out-of-season strawberries, a banana, or a local apple?",
      "alternatives": [
        {"choice": "Strawberries", "co2": 14},
        {"choice": "Banana", "co2": 12},
        {"choice": "Local apple", "co2": 4}
      ],
      "difficulty": "Easy"
    },
    {
      "scenario": "Washing hands. How do you dry them?",
      "alternatives": [
        {"choice": "Paper towels", "co2": 6},
        {"choice": "Hand dryer", "co2": 3},
        {"choice": "Cotton towel", "co2": 2}
      ],
      "difficulty": "Easy"
    },
    {
      "scenario": "Buying beer. Which packaging do you choose?",
      "alternatives": [
        {"choice": "Glass bottle (no recycle)", "co2": 12},
        {"choice": "Can", "co2": 8},
        {"choice": "Keg draft", "co2": 4}
      ],
      "difficulty": "Easy"
    },
    {
      "scenario": "Leaving the room. How do you handle the lights?",
      "alternatives": [
        {"choice": "Leave on all night", "co2": 10},
        {"choice": "Motion sensor bulb", "co2": 3},
        {"choice": "Switch off", "co2": 1}
      ],
      "difficulty": "Easy"
    },
    {
      "scenario": "Chewing gum. Which type, if any, do you pick?",
      "alternatives": [
        {"choice": "Synthetic", "co2": 5},
        {"choice": "Natural gum", "co2": 2},
        {"choice": "No gum", "co2": 0}
      ],
      "difficulty": "Easy"
    },
    {
      "scenario": "Snack time. Which packaging option do you pick?",
      "alternatives": [
        {"choice": "Mini packs", "co2": 10},
        {"choice": "Family pack", "co2": 4},
        {"choice": "Bulk loose nuts", "co2": 2}
      ],
      "difficulty": "Easy"
    },
    {
      "scenario": "Pouring milk for breakfast. Which type do you use?",
      "alternatives": [
        {"choice": "Dairy", "co2": 20},
        {"choice": "Soy", "co2": 12},
        {"choice": "Oat", "co2": 8}
      ],
      "difficulty": "Easy"
    },
    {
      "scenario": "Watching videos online. How do you stream TikTok?",
      "alternatives": [
        {"choice": "TikTok on mobile data", "co2": 8},
        {"choice": "TikTok on WiFi", "co2": 4},
        {"choice": "No TikTok", "co2": 0}
      ],
      "difficulty": "Easy"
    }
]
}